peekSSD/__init__.py
peekSSD/show_spec.py
peekSSD/show_stable.py
peekSSD/gnuplot/gnuplot_128k_SR.conf
peekSSD/gnuplot/gnuplot_128k_SW.conf
peekSSD/gnuplot/gnuplot_4k_RR.conf
peekSSD/gnuplot/gnuplot_4k_RR_latency.conf
peekSSD/gnuplot/gnuplot_4k_RW.conf
peekSSD/gnuplot/gnuplot_4k_RW_latency.conf
peekSSD/gnuplot/gnuplot_8k_RR.conf
peekSSD/gnuplot/gnuplot_8k_RW.conf
peekSSD/gnuplot/pcie/gnuplot_128k_SR.conf
peekSSD/gnuplot/pcie/gnuplot_128k_SW.conf
peekSSD/gnuplot/pcie/gnuplot_4k_RR.conf
peekSSD/gnuplot/pcie/gnuplot_4k_RR_latency.conf
peekSSD/gnuplot/pcie/gnuplot_4k_RW.conf
peekSSD/gnuplot/pcie/gnuplot_4k_RW_latency.conf
peekSSD/gnuplot/pcie/gnuplot_8k_RR.conf
peekSSD/gnuplot/pcie/gnuplot_8k_RW.conf
peekSSD/gnuplot/sata/gnuplot_128k_SR.conf
peekSSD/gnuplot/sata/gnuplot_128k_SW.conf
peekSSD/gnuplot/sata/gnuplot_4k_RR.conf
peekSSD/gnuplot/sata/gnuplot_4k_RR_latency.conf
peekSSD/gnuplot/sata/gnuplot_4k_RW.conf
peekSSD/gnuplot/sata/gnuplot_4k_RW_latency.conf
peekSSD/gnuplot/sata/gnuplot_8k_RR.conf
peekSSD/gnuplot/sata/gnuplot_8k_RW.conf
peekSSD/sh/bandwidth_128k_SR.sh
peekSSD/sh/bandwidth_128k_SW.sh
peekSSD/sh/iops_4k_RR.sh
peekSSD/sh/iops_4k_RW.sh
peekSSD/sh/iops_8k_RR.sh
peekSSD/sh/iops_8k_RW.sh
peekSSD/sh/latency_4k_RR.sh
peekSSD/sh/latency_4k_RW.sh
peekSSD-1.0.5.dist-info/DESCRIPTION.rst
peekSSD-1.0.5.dist-info/METADATA
peekSSD-1.0.5.dist-info/RECORD
peekSSD-1.0.5.dist-info/WHEEL
peekSSD-1.0.5.dist-info/entry_points.txt
peekSSD-1.0.5.dist-info/metadata.json
peekSSD-1.0.5.dist-info/top_level.txt
