Metadata-Version: 2.0
Name: peekSSD
Version: 1.0.5
Summary: An APP to peek SSD Device Performance
Home-page: UNKNOWN
Author: Shannon FAE Team
Author-email: pingyu@shannon-data.com
License: UNKNOWN
Platform: UNKNOWN
Classifier: Development Status :: 3 - Alpha
Classifier: Intended Audience :: Developers
Classifier: Topic :: Software Development :: Build Tools
Classifier: License :: OSI Approved :: MIT License
Classifier: Programming Language :: Python :: 2
Classifier: Programming Language :: Python :: 2.6
Classifier: Programming Language :: Python :: 2.7
